superpowered/__init__.py
superpowered/auth.py
superpowered/chat.py
superpowered/documents.py
superpowered/errors.json
superpowered/exceptions.py
superpowered/items.py
superpowered/knowledge_bases.py
superpowered/query.py
superpowered/superpowered.py
superpowered/usage.py
superpowered/web_search_presets.py
superpowered_sdk-0.1.43.dist-info/METADATA
superpowered_sdk-0.1.43.dist-info/WHEEL
superpowered_sdk-0.1.43.dist-info/top_level.txt
superpowered_sdk-0.1.43.dist-info/RECORD
