Metadata-Version: 2.1
Name: superpowered-sdk
Version: 0.1.43
Summary: Superpowered AI SDK
Home-page: https://superpowered.ai
Author: superpowered
Author-email: justin@superpowered.ai
License: Proprietary License
Project-URL: Homepage, https://superpowered.ai
Project-URL: Documentation, https://superpowered.ai/docs
Project-URL: Contact, https://superpowered.ai/contact/
Project-URL: End-User License Agreement, https://superpowered.ai/api-user-agreement/
Keywords: Superpowered AI Knowledge base as a service for LLM applications
Platform: UNKNOWN
Classifier: Development Status :: 5 - Production/Stable
Classifier: Environment :: Console
Classifier: Environment :: Other Environment
Classifier: Intended Audience :: Developers
Classifier: Intended Audience :: Information Technology
Classifier: Intended Audience :: Science/Research
Classifier: License :: Other/Proprietary License
Classifier: Operating System :: OS Independent
Classifier: Programming Language :: Python :: 3.9
Classifier: Programming Language :: Python :: 3.10
Classifier: Programming Language :: Python :: 3.11
Classifier: Programming Language :: Python :: 3.12
Classifier: Topic :: Database
Classifier: Topic :: Software Development
Classifier: Topic :: Software Development :: Libraries
Classifier: Topic :: Software Development :: Libraries :: Application Frameworks
Classifier: Topic :: Software Development :: Libraries :: Python Modules
Requires-Python: >=3.9
Requires-Dist: requests ==2.29.0
Requires-Dist: tqdm
